<?xml version="1.0" encoding="UTF-8"?>
<!DOCTYPE markables SYSTEM "markables.dtd">
<markables xmlns="www.eml.org/NameSpaces/coref">
<markable id="markable_307" span="word_2616..word_2627" coref_class="set_71"  mmax_level="coref"  sure="yes"  np_form="def-np" />
<markable id="markable_308" span="word_2638..word_2640" coref_class="set_108"  mmax_level="coref"  sure="yes"  np_form="ne" />
<markable id="markable_305" span="word_2585..word_2596" coref_class="set_70"  mmax_level="coref"  sure="yes"  np_form="def-np" />
<markable id="markable_306" span="word_2604..word_2605" coref_class="set_71"  mmax_level="coref"  sure="yes"  np_form="indef-np" />
<markable id="markable_309" span="word_2638..word_2643" coref_class="set_109"  mmax_level="coref"  sure="yes"  np_form="def-np" />
<markable id="markable_102" span="word_3267..word_3269" coref_class="set_87"  mmax_level="coref"  sure="yes"  np_form="def-np" />
<markable id="markable_66" span="word_4036" coref_class="set_0"  mmax_level="coref"  sure="yes"  np_form="ppos" />
<markable id="markable_67" span="word_4056" coref_class="set_0"  mmax_level="coref"  sure="yes"  np_form="ppos" />
<markable id="markable_68" span="word_4085" coref_class="set_0"  mmax_level="coref"  sure="yes"  np_form="ppos" />
<markable id="markable_69" span="word_4103" coref_class="set_0"  mmax_level="coref"  sure="yes"  np_form="ppos" />
<markable id="markable_62" span="word_3794" coref_class="set_0"  mmax_level="coref"  sure="yes"  np_form="ppos" />
<markable id="markable_311" span="word_2667..word_2668" coref_class="set_74"  mmax_level="coref"  sure="yes"  np_form="def-np" />
<markable id="markable_63" span="word_3851" coref_class="set_0"  mmax_level="coref"  sure="yes"  np_form="ppos" />
<markable id="markable_310" span="word_2658" coref_class="set_74"  mmax_level="coref"  sure="yes"  np_form="indef-np" />
<markable id="markable_64" span="word_3889" coref_class="set_0"  mmax_level="coref"  sure="yes"  np_form="ppos" />
<markable id="markable_65" span="word_4010" coref_class="set_0"  mmax_level="coref"  sure="yes"  np_form="pper" />
<markable id="markable_60" span="word_3723" coref_class="set_0"  mmax_level="coref"  sure="yes"  np_form="pper" />
<markable id="markable_61" span="word_3765" coref_class="set_0"  mmax_level="coref"  sure="yes"  np_form="ppos" />
<markable id="markable_77" span="word_4245" coref_class="set_0"  mmax_level="coref"  sure="yes"  np_form="ppos" />
<markable id="markable_75" span="word_4220" coref_class="set_0"  mmax_level="coref"  sure="yes"  np_form="ppos" />
<markable id="markable_76" span="word_4240" coref_class="set_0"  mmax_level="coref"  sure="yes"  np_form="pper" />
<markable id="markable_73" span="word_4195" coref_class="set_0"  mmax_level="coref"  sure="yes"  np_form="ppos" />
<markable id="markable_300" span="word_2473..word_2478" coref_class="set_108"  mmax_level="coref"  sure="yes"  np_form="ne" />
<markable id="markable_74" span="word_4216" coref_class="set_0"  mmax_level="coref"  sure="yes"  np_form="pper" />
<markable id="markable_71" span="word_4156" coref_class="set_0"  mmax_level="coref"  sure="yes"  np_form="ppos" />
<markable id="markable_302" span="word_2495..word_2496" coref_class="set_109"  mmax_level="coref"  sure="yes"  np_form="def-np" />
<markable id="markable_72" span="word_4185" coref_class="set_110"  mmax_level="coref"  sure="yes"  np_form="prefl" />
<markable id="markable_301" span="word_2473..word_2492" coref_class="set_109"  mmax_level="coref"  sure="yes"  np_form="def-np" />
<markable id="markable_304" span="word_2574..word_2583" coref_class="set_70"  mmax_level="coref"  sure="yes"  np_form="def-np" />
<markable id="markable_70" span="word_4130" coref_class="set_0"  mmax_level="coref"  sure="yes"  np_form="ppos" />
<markable id="markable_303" span="word_2511..word_2517" coref_class="set_75"  mmax_level="coref"  sure="yes"  np_form="ne" />
<markable id="markable_44" span="word_2832" coref_class="set_0"  mmax_level="coref"  sure="yes"  np_form="pper" />
<markable id="markable_45" span="word_2874" coref_class="set_0"  mmax_level="coref"  sure="yes"  np_form="pper" />
<markable id="markable_46" span="word_2939" coref_class="set_0"  mmax_level="coref"  sure="yes"  np_form="pper" />
<markable id="markable_47" span="word_2972" coref_class="set_0"  mmax_level="coref"  sure="yes"  np_form="pper" />
<markable id="markable_49" span="word_3046" coref_class="set_0"  mmax_level="coref"  sure="yes"  np_form="pper" />
<markable id="markable_40" span="word_2470" coref_class="set_0"  mmax_level="coref"  sure="yes"  np_form="pper" />
<markable id="markable_42" span="word_2747" coref_class="set_0"  mmax_level="coref"  sure="yes"  np_form="ppos" />
<markable id="markable_43" span="word_2752" coref_class="set_0"  mmax_level="coref"  sure="yes"  np_form="pper" />
<markable id="markable_57" span="word_3494" coref_class="set_0"  mmax_level="coref"  sure="yes"  np_form="pper" />
<markable id="markable_58" span="word_3562" coref_class="set_0"  mmax_level="coref"  sure="yes"  np_form="pper" />
<markable id="markable_55" span="word_3287" coref_class="set_0"  mmax_level="coref"  sure="yes"  np_form="ppos" />
<markable id="markable_56" span="word_3303" coref_class="set_0"  mmax_level="coref"  sure="yes"  np_form="pper" />
<markable id="markable_59" span="word_3592" coref_class="set_0"  mmax_level="coref"  sure="yes"  np_form="pper" />
<markable id="markable_50" span="word_3059" coref_class="set_0"  mmax_level="coref"  sure="yes"  np_form="pper" />
<markable id="markable_53" span="word_3248" coref_class="set_0"  mmax_level="coref"  sure="yes"  np_form="pper" />
<markable id="markable_54" span="word_3281" coref_class="set_0"  mmax_level="coref"  sure="yes"  np_form="pper" />
<markable id="markable_51" span="word_3131" coref_class="set_0"  mmax_level="coref"  sure="yes"  np_form="pper" />
<markable id="markable_413" span="word_1904..word_1906" coref_class="set_95"  mmax_level="coref"  sure="yes"  np_form="ne" />
<markable id="markable_411" span="word_1897" coref_class="set_0"  mmax_level="coref"  sure="yes"  np_form="pper" />
<markable id="markable_410" span="word_4245..word_4246" coref_class="set_114"  mmax_level="coref"  sure="yes"  np_form="def-np" />
<markable id="markable_160" span="word_134..word_141" coref_class="set_121"  mmax_level="coref"  sure="yes"  np_form="indef-np" />
<markable id="markable_162" span="word_155..word_158" coref_class="set_10"  mmax_level="coref"  sure="yes"  np_form="indef-np" />
<markable id="markable_164" span="word_248..word_259" coref_class="set_11"  mmax_level="coref"  sure="yes"  np_form="indef-np" />
<markable id="markable_146" span="word_1..word_3" coref_class="set_5"  mmax_level="coref"  sure="yes"  np_form="indef-np" />
<markable id="markable_408" span="word_4220..word_4222" coref_class="set_114"  mmax_level="coref"  sure="yes"  np_form="def-np" />
<markable id="markable_149" span="word_70..word_71" coref_class="set_120"  mmax_level="coref"  sure="yes"  np_form="def-np" />
<markable id="markable_406" span="word_4183" coref_class="set_110"  mmax_level="coref"  sure="yes"  np_form="indef-np" />
<markable id="markable_407" span="word_4195..word_4196" coref_class="set_114"  mmax_level="coref"  sure="yes"  np_form="def-np" />
<markable id="markable_404" span="word_4130..word_4131" coref_class="set_114"  mmax_level="coref"  sure="yes"  np_form="def-np" />
<markable id="markable_148" span="word_58..word_59" coref_class="set_6"  mmax_level="coref"  sure="yes"  np_form="def-np" />
<markable id="markable_405" span="word_4156..word_4157" coref_class="set_114"  mmax_level="coref"  sure="yes"  np_form="def-np" />
<markable id="markable_401" span="word_4092..word_4094" coref_class="set_108"  mmax_level="coref"  sure="yes"  np_form="ne" />
<markable id="markable_400" span="word_4085..word_4086" coref_class="set_114"  mmax_level="coref"  sure="yes"  np_form="def-np" />
<markable id="markable_403" span="word_4103..word_4104" coref_class="set_114"  mmax_level="coref"  sure="yes"  np_form="def-np" />
<markable id="markable_402" span="word_4092..word_4098" coref_class="set_109"  mmax_level="coref"  sure="yes"  np_form="def-np" />
<markable id="markable_171" span="word_377..word_381" coref_class="set_21"  mmax_level="coref"  sure="yes"  np_form="ne" />
<markable id="markable_150" span="word_35..word_36" coref_class="set_6"  mmax_level="coref"  sure="yes"  np_form="indef-np" />
<markable id="markable_175" span="word_456..word_473" coref_class="set_114"  mmax_level="coref"  sure="yes"  np_form="indef-np" />
<markable id="markable_152" span="word_73..word_84" coref_class="set_114"  mmax_level="coref"  sure="yes"  np_form="indef-np" />
<markable id="markable_178" span="word_479..word_482" coref_class="set_15"  mmax_level="coref"  sure="yes"  np_form="indef-np" />
<markable id="markable_179" span="word_484..word_497" coref_class="set_15"  mmax_level="coref"  sure="yes"  np_form="def-np" />
<markable id="markable_155" span="word_99..word_101" coref_class="set_7"  mmax_level="coref"  sure="yes"  np_form="def-np" />
<markable id="markable_176" span="word_468..word_473" coref_class="set_50"  mmax_level="coref"  sure="yes"  np_form="ne" />
<markable id="markable_156" span="word_82..word_84" coref_class="set_7"  mmax_level="coref"  sure="yes"  np_form="indef-np" />
<markable id="markable_177" span="word_476..word_477" coref_class="set_114"  mmax_level="coref"  sure="yes"  np_form="def-np" />
<markable id="markable_157" span="word_113..word_117" coref_class="set_114"  mmax_level="coref"  sure="yes"  np_form="def-np" />
<markable id="markable_183" span="word_603..word_605" coref_class="set_114"  mmax_level="coref"  sure="yes"  np_form="def-np" />
<markable id="markable_286" span="word_2117..word_2118" coref_class="set_60"  mmax_level="coref"  sure="yes"  np_form="def-np" />
<markable id="markable_287" span="word_2127..word_2129" coref_class="set_61"  mmax_level="coref"  sure="yes"  np_form="def-np" />
<markable id="markable_288" span="word_2087..word_2089" coref_class="set_61"  mmax_level="coref"  sure="yes"  np_form="indef-np" />
<markable id="markable_289" span="word_2183..word_2185" coref_class="set_62"  mmax_level="coref"  sure="yes"  np_form="def-np" />
<markable id="markable_180" span="word_509..word_511" coref_class="set_15"  mmax_level="coref"  sure="yes"  np_form="def-np" />
<markable id="markable_181" span="word_513..word_516" coref_class="set_16"  mmax_level="coref"  sure="yes"  np_form="indef-np" />
<markable id="markable_182" span="word_538..word_539" coref_class="set_16"  mmax_level="coref"  sure="yes"  np_form="def-np" />
<markable id="markable_280" span="word_2034..word_2037" coref_class="set_114"  mmax_level="coref"  sure="yes"  np_form="def-np" />
<markable id="markable_281" span="word_2042..word_2045" coref_class="set_58"  mmax_level="coref"  sure="yes"  np_form="def-np" />
<markable id="markable_282" span="word_2047..word_2049" coref_class="set_114"  mmax_level="coref"  sure="yes"  np_form="def-np" />
<markable id="markable_188" span="word_662..word_663" coref_class="set_18"  mmax_level="coref"  sure="yes"  np_form="def-np" />
<markable id="markable_283" span="word_2079..word_2081" coref_class="set_62"  mmax_level="coref"  sure="yes"  np_form="indef-np" />
<markable id="markable_285" span="word_2095..word_2096" coref_class="set_60"  mmax_level="coref"  sure="yes"  np_form="indef-np" />
<markable id="markable_421" span="word_3552..word_3554" coref_class="set_111"  mmax_level="coref"  sure="yes"  np_form="def-np" />
<markable id="markable_420" span="word_3546..word_3547" coref_class="set_112"  mmax_level="coref"  sure="yes"  np_form="def-np" />
<markable id="markable_196" span="word_701" coref_class="set_21"  mmax_level="coref"  sure="yes"  np_form="ne" />
<markable id="markable_299" span="word_2450..word_2451" coref_class="set_66"  mmax_level="coref"  sure="yes"  np_form="def-np" />
<markable id="markable_197" span="word_755" coref_class="set_21"  mmax_level="coref"  sure="yes"  np_form="ne" />
<markable id="markable_190" span="word_682..word_684" coref_class="set_18"  mmax_level="coref"  sure="yes"  np_form="def-np" />
<markable id="markable_191" span="word_696..word_699" coref_class="set_21"  mmax_level="coref"  sure="yes"  np_form="ne" />
<markable id="markable_415" span="word_2351" coref_class="set_0"  mmax_level="coref"  sure="yes"  np_form="pper" />
<markable id="markable_291" span="word_2226..word_2245" coref_class="set_65"  mmax_level="coref"  sure="yes"  np_form="indef-np" />
<markable id="markable_292" span="word_2231..word_2234" coref_class="set_63"  mmax_level="coref"  sure="yes"  np_form="indef-np" />
<markable id="markable_417" span="word_2374" coref_class="set_0"  mmax_level="coref"  sure="yes"  np_form="pper" />
<markable id="markable_99" span="word_3085..word_3088" coref_class="set_87"  mmax_level="coref"  sure="yes"  np_form="indef-np" />
<markable id="markable_419" span="word_3537..word_3538" coref_class="set_113"  mmax_level="coref"  sure="yes"  np_form="def-np" />
<markable id="markable_295" span="word_2288..word_2289" coref_class="set_65"  mmax_level="coref"  sure="yes"  np_form="def-np" />
<markable id="markable_198" span="word_788..word_791" coref_class="set_24"  mmax_level="coref"  sure="yes"  np_form="ne" />
<markable id="markable_294" span="word_2277..word_2278" coref_class="set_65"  mmax_level="coref"  sure="yes"  np_form="def-np" />
<markable id="markable_258" span="word_1632..word_1633" coref_class="set_58"  mmax_level="coref"  sure="yes"  np_form="def-np" />
<markable id="markable_257" span="word_1625..word_1630" coref_class="set_95"  mmax_level="coref"  sure="yes"  np_form="ne" />
<markable id="markable_391" span="word_3896..word_3908" coref_class="set_101"  mmax_level="coref"  sure="yes"  np_form="indef-np" />
<markable id="markable_390" span="word_3919..word_3920" coref_class="set_101"  mmax_level="coref"  sure="yes"  np_form="def-np" />
<markable id="markable_393" span="word_3939..word_3941" coref_class="set_108"  mmax_level="coref"  sure="yes"  np_form="ne" />
<markable id="markable_392" span="word_3931..word_3933" coref_class="set_114"  mmax_level="coref"  sure="yes"  np_form="def-np" />
<markable id="markable_256" span="word_1610..word_1615" coref_class="set_50"  mmax_level="coref"  sure="yes"  np_form="ne" />
<markable id="markable_395" span="word_4013..word_4031" coref_class="set_114"  mmax_level="coref"  sure="yes"  np_form="indef-np" />
<markable id="markable_255" span="word_1603..word_1606" coref_class="set_58"  mmax_level="coref"  sure="yes"  np_form="def-np" />
<markable id="markable_394" span="word_3939..word_3945" coref_class="set_109"  mmax_level="coref"  sure="yes"  np_form="def-np" />
<markable id="markable_397" span="word_4056..word_4059" coref_class="set_114"  mmax_level="coref"  sure="yes"  np_form="def-np" />
<markable id="markable_396" span="word_4036..word_4038" coref_class="set_114"  mmax_level="coref"  sure="yes"  np_form="def-np" />
<markable id="markable_252" span="word_1579..word_1584" coref_class="set_114"  mmax_level="coref"  sure="yes"  np_form="def-np" />
<markable id="markable_399" span="word_4065..word_4077" coref_class="set_109"  mmax_level="coref"  sure="yes"  np_form="def-np" />
<markable id="markable_251" span="word_1568..word_1577" coref_class="set_58"  mmax_level="coref"  sure="yes"  np_form="indef-np" />
<markable id="markable_398" span="word_4065..word_4070" coref_class="set_108"  mmax_level="coref"  sure="yes"  np_form="ne" />
<markable id="markable_16" span="word_1447" coref_class="set_0"  mmax_level="coref"  sure="yes"  np_form="pper" />
<markable id="markable_15" span="word_1432" coref_class="set_0"  mmax_level="coref"  sure="yes"  np_form="ppos" />
<markable id="markable_18" span="word_1495" coref_class="set_0"  mmax_level="coref"  sure="yes"  np_form="ppos" />
<markable id="markable_17" span="word_1458" coref_class="set_0"  mmax_level="coref"  sure="yes"  np_form="ppos" />
<markable id="markable_11" span="word_1312" coref_class="set_30"  mmax_level="coref"  sure="yes"  np_form="pper" />
<markable id="markable_14" span="word_1396" coref_class="set_0"  mmax_level="coref"  sure="yes"  np_form="ppos" />
<markable id="markable_13" span="word_1357" coref_class="set_0"  mmax_level="coref"  sure="yes"  np_form="ppos" />
<markable id="markable_455" span="word_577..word_578" coref_class="set_120"  mmax_level="coref"  sure="yes"  np_form="def-np" />
<markable id="markable_457" span="word_600..word_601" coref_class="set_123"  mmax_level="coref"  sure="yes"  np_form="ne" />
<markable id="markable_10" span="word_1258" coref_class="set_36"  mmax_level="coref"  sure="yes"  np_form="pper" />
<markable id="markable_451" span="word_145..word_149" coref_class="set_115"  mmax_level="coref"  sure="yes"  np_form="indef-np" />
<markable id="markable_452" span="word_151..word_168" coref_class="set_115"  mmax_level="coref"  sure="yes"  np_form="def-np" />
<markable id="markable_454" span="word_452..word_453" coref_class="set_120"  mmax_level="coref"  sure="yes"  np_form="def-np" />
<markable id="markable_249" span="word_1537..word_1543" coref_class="set_95"  mmax_level="coref"  sure="yes"  np_form="ne" />
<markable id="markable_380" span="word_3602..word_3607" coref_class="set_95"  mmax_level="coref"  sure="yes"  np_form="ne" />
<markable id="markable_248" span="word_1499..word_1506" coref_class="set_46"  mmax_level="coref"  sure="yes"  np_form="def-np" />
<markable id="markable_247" span="word_1463..word_1470" coref_class="set_46"  mmax_level="coref"  sure="yes"  np_form="def-np" />
<markable id="markable_246" span="word_1499..word_1504" coref_class="set_45"  mmax_level="coref"  sure="yes"  np_form="ne" />
<markable id="markable_245" span="word_1495..word_1496" coref_class="set_114"  mmax_level="coref"  sure="yes"  np_form="def-np" />
<markable id="markable_384" span="word_3782..word_3787" coref_class="set_108"  mmax_level="coref"  sure="yes"  np_form="ne" />
<markable id="markable_243" span="word_1465..word_1470" coref_class="set_45"  mmax_level="coref"  sure="yes"  np_form="ne" />
<markable id="markable_242" span="word_1458..word_1459" coref_class="set_114"  mmax_level="coref"  sure="yes"  np_form="def-np" />
<markable id="markable_241" span="word_1435..word_1436" coref_class="set_41"  mmax_level="coref"  sure="yes"  np_form="indef-np" />
<markable id="markable_388" span="word_3851..word_3853" coref_class="set_114"  mmax_level="coref"  sure="yes"  np_form="def-np" />
<markable id="markable_240" span="word_1452..word_1454" coref_class="set_41"  mmax_level="coref"  sure="yes"  np_form="def-np" />
<markable id="markable_387" span="word_3816..word_3820" coref_class="set_109"  mmax_level="coref"  sure="yes"  np_form="def-np" />
<markable id="markable_386" span="word_3794..word_3798" coref_class="set_114"  mmax_level="coref"  sure="yes"  np_form="def-np" />
<markable id="markable_385" span="word_3782..word_3792" coref_class="set_109"  mmax_level="coref"  sure="yes"  np_form="def-np" />
<markable id="markable_389" span="word_3889..word_3892" coref_class="set_114"  mmax_level="coref"  sure="yes"  np_form="def-np" />
<markable id="markable_239" span="word_1439..word_1444" coref_class="set_40"  mmax_level="coref"  sure="yes"  np_form="ne" />
<markable id="markable_277" span="word_1996..word_2001" coref_class="set_95"  mmax_level="coref"  sure="yes"  np_form="ne" />
<markable id="markable_378" span="word_3567..word_3569" coref_class="set_94"  mmax_level="coref"  sure="yes"  np_form="def-np" />
<markable id="markable_8" span="word_641" coref_class="set_0"  mmax_level="coref"  sure="yes"  np_form="ppos" />
<markable id="markable_375" span="word_3505..word_3510" coref_class="set_112"  mmax_level="coref"  sure="yes"  np_form="def-np" />
<markable id="markable_374" span="word_3497..word_3503" coref_class="set_113"  mmax_level="coref"  sure="yes"  np_form="def-np" />
<markable id="markable_376" span="word_3517..word_3520" coref_class="set_111"  mmax_level="coref"  sure="yes"  np_form="def-np" />
<markable id="markable_34" span="word_2047" coref_class="set_0"  mmax_level="coref"  sure="yes"  np_form="ppos" />
<markable id="markable_33" span="word_2034" coref_class="set_0"  mmax_level="coref"  sure="yes"  np_form="ppos" />
<markable id="markable_36" span="word_2238" coref_class="set_63"  mmax_level="coref"  sure="yes"  np_form="ppos" />
<markable id="markable_35" span="word_2201" coref_class="set_0"  mmax_level="coref"  sure="yes"  np_form="pper" />
<markable id="markable_38" span="word_2325" coref_class="set_0"  mmax_level="coref"  sure="yes"  np_form="ppos" />
<markable id="markable_470" span="word_2915..word_2922" coref_class="set_122"  mmax_level="coref"  sure="yes"  np_form="indef-np" />
<markable id="markable_37" span="word_2243" coref_class="set_63"  mmax_level="coref"  sure="yes"  np_form="ppos" />
<markable id="markable_473" span="word_3574..word_3575" coref_class="set_123"  mmax_level="coref"  sure="yes"  np_form="ne" />
<markable id="markable_30" span="word_2003" coref_class="set_0"  mmax_level="coref"  sure="yes"  np_form="pper" />
<markable id="markable_32" span="word_2031" coref_class="set_0"  mmax_level="coref"  sure="yes"  np_form="pper" />
<markable id="markable_267" span="word_1808..word_1809" coref_class="set_54"  mmax_level="coref"  sure="yes"  np_form="def-np" />
<markable id="markable_266" span="word_1781..word_1787" coref_class="set_54"  mmax_level="coref"  sure="yes"  np_form="indef-np" />
<markable id="markable_361" span="word_3365..word_3366" coref_class="set_91"  mmax_level="coref"  sure="yes"  np_form="def-np" />
<markable id="markable_268" span="word_1813..word_1814" coref_class="set_66"  mmax_level="coref"  sure="yes"  np_form="def-np" />
<markable id="markable_369" span="word_3422..word_3424" coref_class="set_93"  mmax_level="coref"  sure="yes"  np_form="def-np" />
<markable id="markable_19" span="word_1513" coref_class="set_0"  mmax_level="coref"  sure="yes"  np_form="pper" />
<markable id="markable_263" span="word_1744..word_1745" coref_class="set_66"  mmax_level="coref"  sure="yes"  np_form="def-np" />
<markable id="markable_7" span="word_637" coref_class="set_0"  mmax_level="coref"  sure="yes"  np_form="ppos" />
<markable id="markable_6" span="word_603" coref_class="set_0"  mmax_level="coref"  sure="yes"  np_form="ppos" />
<markable id="markable_24" span="word_1718" coref_class="set_0"  mmax_level="coref"  sure="yes"  np_form="pper" />
<markable id="markable_5" span="word_587" coref_class="set_0"  mmax_level="coref"  sure="yes"  np_form="pper" />
<markable id="markable_23" span="word_1603" coref_class="set_0"  mmax_level="coref"  sure="yes"  np_form="ppos" />
<markable id="markable_4" span="word_269" coref_class="set_11"  mmax_level="coref"  sure="yes"  np_form="ppos" />
<markable id="markable_22" span="word_1579" coref_class="set_0"  mmax_level="coref"  sure="yes"  np_form="ppos" />
<markable id="markable_3" span="word_164" coref_class="set_10"  mmax_level="coref"  sure="yes"  np_form="ppos" />
<markable id="markable_29" span="word_1990" coref_class="set_0"  mmax_level="coref"  sure="yes"  np_form="pper" />
<markable id="markable_461" span="word_960..word_962" coref_class="set_118"  mmax_level="coref"  sure="yes"  np_form="indef-np" />
<markable id="markable_2" span="word_19" coref_class="set_5"  mmax_level="coref"  sure="yes"  np_form="ppos" />
<markable id="markable_28" span="word_1881" coref_class="set_0"  mmax_level="coref"  sure="yes"  np_form="pper" />
<markable id="markable_1" span="word_9" coref_class="set_5"  mmax_level="coref"  sure="yes"  np_form="pper" />
<markable id="markable_27" span="word_1850" coref_class="set_0"  mmax_level="coref"  sure="yes"  np_form="pper" />
<markable id="markable_26" span="word_1747" coref_class="set_0"  mmax_level="coref"  sure="yes"  np_form="pper" />
<markable id="markable_464" span="word_1263..word_1267" coref_class="set_119"  mmax_level="coref"  sure="yes"  np_form="def-np" />
<markable id="markable_465" span="word_1318..word_1320" coref_class="set_119"  mmax_level="coref"  sure="yes"  np_form="ne" />
<markable id="markable_462" span="word_968..word_969" coref_class="set_118"  mmax_level="coref"  sure="yes"  np_form="def-np" />
<markable id="markable_21" span="word_1557" coref_class="set_0"  mmax_level="coref"  sure="yes"  np_form="pper" />
<markable id="markable_20" span="word_1532" coref_class="set_0"  mmax_level="coref"  sure="yes"  np_form="pper" />
<markable id="markable_466" span="word_1409..word_1419" coref_class="set_121"  mmax_level="coref"  sure="yes"  np_form="def-np" />
<markable id="markable_352" span="word_3287..word_3289" coref_class="set_94"  mmax_level="coref"  sure="yes"  np_form="def-np" />
<markable id="markable_358" span="word_3326..word_3360" coref_class="set_91"  mmax_level="coref"  sure="yes"  np_form="indef-np" />
<markable id="markable_359" span="word_3344" coref_class="set_89"  mmax_level="coref"  sure="yes"  np_form="ne" />
<markable id="markable_215" span="word_1169..word_1174" coref_class="set_45"  mmax_level="coref"  sure="yes"  np_form="ne" />
<markable id="markable_212" span="word_1102..word_1107" coref_class="set_40"  mmax_level="coref"  sure="yes"  np_form="ne" />
<markable id="markable_209" span="word_1049..word_1052" coref_class="set_24"  mmax_level="coref"  sure="yes"  np_form="ne" />
<markable id="markable_349" span="word_3257" coref_class="set_89"  mmax_level="coref"  sure="yes"  np_form="ne" />
<markable id="markable_343" span="word_3111..word_3124" coref_class="set_94"  mmax_level="coref"  sure="yes"  np_form="indef-np" />
<markable id="markable_204" span="word_877..word_883" coref_class="set_75"  mmax_level="coref"  sure="yes"  np_form="ne" />
<markable id="markable_202" span="word_860..word_861" coref_class="set_22"  mmax_level="coref"  sure="yes"  np_form="def-np" />
<markable id="markable_203" span="word_863..word_868" coref_class="set_108"  mmax_level="coref"  sure="yes"  np_form="ne" />
<markable id="markable_201" span="word_844..word_845" coref_class="set_22"  mmax_level="coref"  sure="yes"  np_form="indef-np" />
<markable id="markable_340" span="word_3072..word_3092" coref_class="set_93"  mmax_level="coref"  sure="yes"  np_form="indef-np" />
<markable id="markable_338" span="word_3061..word_3063" coref_class="set_93"  mmax_level="coref"  sure="yes"  np_form="def-np" />
<markable id="markable_335" span="word_2984..word_2986" coref_class="set_122"  mmax_level="coref"  sure="yes"  np_form="def-np" />
<markable id="markable_336" span="word_3048..word_3050" coref_class="set_122"  mmax_level="coref"  sure="yes"  np_form="def-np" />
<markable id="markable_232" span="word_1357..word_1358" coref_class="set_120"  mmax_level="coref"  sure="yes"  np_form="def-np" />
<markable id="markable_235" span="word_1396..word_1397" coref_class="set_114"  mmax_level="coref"  sure="yes"  np_form="def-np" />
<markable id="markable_236" span="word_1404..word_1407" coref_class="set_36"  mmax_level="coref"  sure="yes"  np_form="def-np" />
<markable id="markable_229" span="word_1338..word_1341" coref_class="set_121"  mmax_level="coref"  sure="yes"  np_form="def-np" />
<markable id="markable_228" span="word_313..word_314" coref_class="set_32"  mmax_level="coref"  sure="yes"  np_form="def-np" />
<markable id="markable_328" span="word_2788..word_2790" coref_class="set_83"  mmax_level="coref"  sure="yes"  np_form="def-np" />
<markable id="markable_327" span="word_2907..word_2910" coref_class="set_83"  mmax_level="coref"  sure="yes"  np_form="def-np" />
<markable id="markable_323" span="word_2814" coref_class="set_81"  mmax_level="coref"  sure="yes"  np_form="indef-np" />
<markable id="markable_324" span="word_2821" coref_class="set_82"  mmax_level="coref"  sure="yes"  np_form="ne" />
<markable id="markable_322" span="word_2800..word_2801" coref_class="set_81"  mmax_level="coref"  sure="yes"  np_form="indef-np" />
<markable id="markable_320" span="word_2771" coref_class="set_82"  mmax_level="coref"  sure="yes"  np_form="pds" />
<markable id="markable_223" span="word_1293..word_1295" coref_class="set_50"  mmax_level="coref"  sure="yes"  np_form="ne" />
<markable id="markable_220" span="word_1272..word_1273" coref_class="set_36"  mmax_level="coref"  sure="yes"  np_form="def-np" />
<markable id="markable_221" span="word_1279..word_1284" coref_class="set_50"  mmax_level="coref"  sure="yes"  np_form="ne" />
<markable id="markable_226" span="word_1324..word_1330" coref_class="set_36"  mmax_level="coref"  sure="yes"  np_form="def-np" />
<markable id="markable_227" span="word_294..word_298" coref_class="set_32"  mmax_level="coref"  sure="yes"  np_form="indef-np" />
<markable id="markable_224" span="word_1293..word_1297" coref_class="set_30"  mmax_level="coref"  sure="yes"  np_form="def-np" />
<markable id="markable_225" span="word_1299" coref_class="set_89"  mmax_level="coref"  sure="yes"  np_form="ne" />
<markable id="markable_219" span="word_1269..word_1270" coref_class="set_26"  mmax_level="coref"  sure="yes"  np_form="def-np" />
<markable id="markable_218" span="word_1252..word_1255" coref_class="set_26"  mmax_level="coref"  sure="yes"  np_form="indef-np" />
<markable id="markable_217" span="word_1235..word_1241" coref_class="set_36"  mmax_level="coref"  sure="yes"  np_form="def-np" />
<markable id="markable_319" span="word_2756..word_2769" coref_class="set_82"  mmax_level="coref"  sure="yes"  np_form="def-np" />
<markable id="markable_318" span="word_2758" coref_class="set_89"  mmax_level="coref"  sure="yes"  np_form="ne" />
<markable id="markable_317" span="word_2747..word_2750" coref_class="set_114"  mmax_level="coref"  sure="yes"  np_form="def-np" />
</markables>
